{"data": {"MSFT": [{"symbol": "MSFT", "timestamp": "2023-08-04T04:00:00+00:00", "open": 331.88, "high": 335.14, "low": 327.24, "close": 327.78, "volume": 23598859.0, "trade_count": 427347.0, "vwap": 330.889283}, {"symbol": "MSFT", "timestamp": "2023-08-07T04:00:00+00:00", "open": 328.37, "high": 331.11, "low": 327.52, "close": 330.11, "volume": 18467752.0, "trade_count": 307300.0, "vwap": 329.51545}, {"symbol": "MSFT", "timestamp": "2023-08-08T04:00:00+00:00", "open": 326.96, "high": 328.75, "low": 323.0, "close": 326.05, "volume": 22387590.0, "trade_count": 389453.0, "vwap": 325.140839}, {"symbol": "MSFT", "timestamp": "2023-08-09T04:00:00+00:00", "open": 326.47, "high": 327.11, "low": 321.0499, "close": 322.23, "volume": 22426719.0, "trade_count": 352956.0, "vwap": 323.29615}, {"symbol": "MSFT", "timestamp": "2023-08-10T04:00:00+00:00", "open": 326.015, "high": 328.26, "low": 321.18, "close": 322.93, "volume": 20124283.0, "trade_count": 295452.0, "vwap": 323.999276}, {"symbol": "MSFT", "timestamp": "2023-08-11T04:00:00+00:00", "open": 320.26, "high": 322.41, "low": 319.21, "close": 321.01, "volume": 24606575.0, "trade_count": 353666.0, "vwap": 320.906732}], "PFE": [{"symbol": "PFE", "timestamp": "2023-08-04T04:00:00+00:00", "open": 34.95, "high": 35.34, "low": 34.655, "close": 35.02, "volume": 25466858.0, "trade_count": 142833.0, "vwap": 35.050995}, {"symbol": "PFE", "timestamp": "2023-08-07T04:00:00+00:00", "open": 35.01, "high": 35.855, "low": 34.9, "close": 35.68, "volume": 31072970.0, "trade_count": 146957.0, "vwap": 35.380976}, {"symbol": "PFE", "timestamp": "2023-08-08T04:00:00+00:00", "open": 36.37, "high": 36.37, "low": 35.39, "close": 35.64, "volume": 25233409.0, "trade_count": 164245.0, "vwap": 35.676171}, {"symbol": "PFE", "timestamp": "2023-08-09T04:00:00+00:00", "open": 35.6, "high": 36.06, "low": 35.51, "close": 35.84, "volume": 17220714.0, "trade_count": 112391.0, "vwap": 35.887575}, {"symbol": "PFE", "timestamp": "2023-08-10T04:00:00+00:00", "open": 35.82, "high": 36.09, "low": 35.595, "close": 35.72, "volume": 18955150.0, "trade_count": 110616.0, "vwap": 35.817056}, {"symbol": "PFE", "timestamp": "2023-08-11T04:00:00+00:00", "open": 35.62, "high": 36.28, "low": 35.59, "close": 36.04, "volume": 16473046.0, "trade_count": 99790.0, "vwap": 36.021924}], "SO": [{"symbol": "SO", "timestamp": "2023-08-04T04:00:00+00:00", "open": 68.74, "high": 69.62, "low": 67.505, "close": 67.84, "volume": 4070156.0, "trade_count": 51117.0, "vwap": 68.409064}, {"symbol": "SO", "timestamp": "2023-08-07T04:00:00+00:00", "open": 68.0, "high": 68.53, "low": 67.84, "close": 68.02, "volume": 3197642.0, "trade_count": 37946.0, "vwap": 68.070033}, {"symbol": "SO", "timestamp": "2023-08-08T04:00:00+00:00", "open": 68.01, "high": 68.83, "low": 67.68, "close": 68.81, "volume": 3567776.0, "trade_count": 37757.0, "vwap": 68.397726}, {"symbol": "SO", "timestamp": "2023-08-09T04:00:00+00:00", "open": 68.82, "high": 69.705, "low": 68.75, "close": 69.19, "volume": 3729357.0, "trade_count": 41004.0, "vwap": 69.245648}, {"symbol": "SO", "timestamp": "2023-08-10T04:00:00+00:00", "open": 69.7, "high": 69.97, "low": 69.1, "close": 69.41, "volume": 2583875.0, "trade_count": 38398.0, "vwap": 69.447445}, {"symbol": "SO", "timestamp": "2023-08-11T04:00:00+00:00", "open": 69.34, "high": 69.7, "low": 68.93, "close": 69.5, "volume": 3212415.0, "trade_count": 44846.0, "vwap": 69.452742}], "UAL": [{"symbol": "UAL", "timestamp": "2023-08-04T04:00:00+00:00", "open": 52.45, "high": 52.59, "low": 51.82, "close": 52.37, "volume": 4359830.0, "trade_count": 53246.0, "vwap": 52.281873}, {"symbol": "UAL", "timestamp": "2023-08-07T04:00:00+00:00", "open": 52.98, "high": 53.8, "low": 52.43, "close": 53.68, "volume": 5673980.0, "trade_count": 56051.0, "vwap": 53.210084}, {"symbol": "UAL", "timestamp": "2023-08-08T04:00:00+00:00", "open": 53.02, "high": 54.91, "low": 52.95, "close": 54.86, "volume": 6650108.0, "trade_count": 64343.0, "vwap": 54.210691}, {"symbol": "UAL", "timestamp": "2023-08-09T04:00:00+00:00", "open": 54.77, "high": 54.91, "low": 52.94, "close": 53.13, "volume": 5552127.0, "trade_count": 57787.0, "vwap": 53.597715}, {"symbol": "UAL", "timestamp": "2023-08-10T04:00:00+00:00", "open": 53.47, "high": 53.78, "low": 52.49, "close": 52.95, "volume": 4642479.0, "trade_count": 54898.0, "vwap": 53.070415}, {"symbol": "UAL", "timestamp": "2023-08-11T04:00:00+00:00", "open": 52.59, "high": 52.685, "low": 51.82, "close": 52.26, "volume": 3709393.0, "trade_count": 50183.0, "vwap": 52.296083}], "AMZN": [{"symbol": "AMZN", "timestamp": "2023-08-04T04:00:00+00:00", "open": 141.06, "high": 143.63, "low": 139.32, "close": 139.57, "volume": 152816580.0, "trade_count": 1363042.0, "vwap": 141.390147}, {"symbol": "AMZN", "timestamp": "2023-08-07T04:00:00+00:00", "open": 140.99, "high": 142.54, "low": 138.95, "close": 142.22, "volume": 71251605.0, "trade_count": 660390.0, "vwap": 141.005097}, {"symbol": "AMZN", "timestamp": "2023-08-08T04:00:00+00:00", "open": 140.62, "high": 140.84, "low": 138.42, "close": 139.94, "volume": 51740918.0, "trade_count": 510537.0, "vwap": 139.59373}, {"symbol": "AMZN", "timestamp": "2023-08-09T04:00:00+00:00", "open": 139.97, "high": 140.32, "low": 137.1, "close": 137.85, "volume": 50169099.0, "trade_count": 429632.0, "vwap": 138.322762}, {"symbol": "AMZN", "timestamp": "2023-08-10T04:00:00+00:00", "open": 139.075, "high": 140.41, "low": 137.49, "close": 138.56, "volume": 59051553.0, "trade_count": 460778.0, "vwap": 138.875247}, {"symbol": "AMZN", "timestamp": "2023-08-11T04:00:00+00:00", "open": 137.4, "high": 139.32, "low": 137.0, "close": 138.41, "volume": 42723291.0, "trade_count": 393088.0, "vwap": 138.362292}], "MRK": [{"symbol": "MRK", "timestamp": "2023-08-04T04:00:00+00:00", "open": 105.64, "high": 106.42, "low": 104.51, "close": 105.0, "volume": 6653076.0, "trade_count": 80509.0, "vwap": 105.083818}, {"symbol": "MRK", "timestamp": "2023-08-07T04:00:00+00:00", "open": 105.29, "high": 106.28, "low": 104.42, "close": 106.09, "volume": 8259260.0, "trade_count": 83395.0, "vwap": 105.595361}, {"symbol": "MRK", "timestamp": "2023-08-08T04:00:00+00:00", "open": 105.69, "high": 107.19, "low": 105.69, "close": 106.41, "volume": 10152232.0, "trade_count": 116948.0, "vwap": 106.42115}, {"symbol": "MRK", "timestamp": "2023-08-09T04:00:00+00:00", "open": 106.27, "high": 106.79, "low": 105.79, "close": 106.1, "volume": 6479666.0, "trade_count": 70129.0, "vwap": 106.248197}, {"symbol": "MRK", "timestamp": "2023-08-10T04:00:00+00:00", "open": 106.21, "high": 107.04, "low": 105.42, "close": 105.57, "volume": 6525745.0, "trade_count": 77882.0, "vwap": 106.027278}, {"symbol": "MRK", "timestamp": "2023-08-11T04:00:00+00:00", "open": 105.95, "high": 107.705, "low": 105.59, "close": 107.44, "volume": 5882328.0, "trade_count": 69908.0, "vwap": 107.056568}], "FDX": [{"symbol": "FDX", "timestamp": "2023-08-04T04:00:00+00:00", "open": 265.0, "high": 267.265, "low": 262.57, "close": 263.0, "volume": 1573280.0, "trade_count": 29186.0, "vwap": 263.897124}, {"symbol": "FDX", "timestamp": "2023-08-07T04:00:00+00:00", "open": 263.75, "high": 266.76, "low": 262.24, "close": 264.36, "volume": 1494918.0, "trade_count": 34668.0, "vwap": 263.694862}, {"symbol": "FDX", "timestamp": "2023-08-08T04:00:00+00:00", "open": 263.5, "high": 269.91, "low": 263.29, "close": 268.26, "volume": 2093151.0, "trade_count": 45340.0, "vwap": 267.986166}, {"symbol": "FDX", "timestamp": "2023-08-09T04:00:00+00:00", "open": 267.52, "high": 268.3, "low": 264.97, "close": 265.48, "volume": 1266330.0, "trade_count": 28073.0, "vwap": 266.360024}, {"symbol": "FDX", "timestamp": "2023-08-10T04:00:00+00:00", "open": 266.64, "high": 268.11, "low": 264.99, "close": 266.53, "volume": 1039014.0, "trade_count": 26235.0, "vwap": 266.73816}, {"symbol": "FDX", "timestamp": "2023-08-11T04:00:00+00:00", "open": 265.43, "high": 266.53, "low": 264.0, "close": 265.77, "volume": 1195526.0, "trade_count": 27649.0, "vwap": 265.373559}], "F": [{"symbol": "F", "timestamp": "2023-08-04T04:00:00+00:00", "open": 13.1, "high": 13.1, "low": 12.8, "close": 12.89, "volume": 47784382.0, "trade_count": 128472.0, "vwap": 12.939203}, {"symbol": "F", "timestamp": "2023-08-07T04:00:00+00:00", "open": 12.93, "high": 12.96, "low": 12.78, "close": 12.94, "volume": 43941628.0, "trade_count": 114266.0, "vwap": 12.873839}, {"symbol": "F", "timestamp": "2023-08-08T04:00:00+00:00", "open": 12.77, "high": 12.9, "low": 12.7, "close": 12.88, "volume": 45150963.0, "trade_count": 111101.0, "vwap": 12.808732}, {"symbol": "F", "timestamp": "2023-08-09T04:00:00+00:00", "open": 12.77, "high": 12.83, "low": 12.66, "close": 12.73, "volume": 43014108.0, "trade_count": 110366.0, "vwap": 12.754217}, {"symbol": "F", "timestamp": "2023-08-10T04:00:00+00:00", "open": 12.78, "high": 12.78, "low": 12.08, "close": 12.16, "volume": 104063861.0, "trade_count": 245272.0, "vwap": 12.303515}, {"symbol": "F", "timestamp": "2023-08-11T04:00:00+00:00", "open": 12.12, "high": 12.2, "low": 12.0, "close": 12.14, "volume": 64235079.0, "trade_count": 159961.0, "vwap": 12.102357}], "GD": [{"symbol": "GD", "timestamp": "2023-08-04T04:00:00+00:00", "open": 226.69, "high": 227.5, "low": 223.56, "close": 224.01, "volume": 1183296.0, "trade_count": 28378.0, "vwap": 225.225474}, {"symbol": "GD", "timestamp": "2023-08-07T04:00:00+00:00", "open": 224.83, "high": 227.44, "low": 224.83, "close": 227.19, "volume": 1022988.0, "trade_count": 29080.0, "vwap": 226.823337}, {"symbol": "GD", "timestamp": "2023-08-08T04:00:00+00:00", "open": 226.21, "high": 226.88, "low": 223.76, "close": 224.47, "volume": 1002738.0, "trade_count": 25661.0, "vwap": 224.538544}, {"symbol": "GD", "timestamp": "2023-08-09T04:00:00+00:00", "open": 225.0, "high": 227.02, "low": 224.47, "close": 226.14, "volume": 1079965.0, "trade_count": 24891.0, "vwap": 225.850748}, {"symbol": "GD", "timestamp": "2023-08-10T04:00:00+00:00", "open": 226.18, "high": 227.225, "low": 225.18, "close": 225.66, "volume": 861283.0, "trade_count": 23891.0, "vwap": 225.993329}, {"symbol": "GD", "timestamp": "2023-08-11T04:00:00+00:00", "open": 225.67, "high": 228.73, "low": 225.505, "close": 226.99, "volume": 1203232.0, "trade_count": 25946.0, "vwap": 227.290658}], "META": [{"symbol": "META", "timestamp": "2023-08-04T04:00:00+00:00", "open": 314.96, "high": 318.41, "low": 310.2, "close": 310.73, "volume": 18331525.0, "trade_count": 243229.0, "vwap": 313.448423}, {"symbol": "META", "timestamp": "2023-08-07T04:00:00+00:00", "open": 313.23, "high": 317.07, "low": 310.46, "close": 316.56, "volume": 16357608.0, "trade_count": 230813.0, "vwap": 314.192591}, {"symbol": "META", "timestamp": "2023-08-08T04:00:00+00:00", "open": 314.4, "high": 317.89, "low": 310.11, "close": 312.64, "volume": 15195093.0, "trade_count": 233406.0, "vwap": 312.898173}, {"symbol": "META", "timestamp": "2023-08-09T04:00:00+00:00", "open": 312.88, "high": 313.63, "low": 302.85, "close": 305.21, "volume": 19974542.0, "trade_count": 283925.0, "vwap": 306.871705}, {"symbol": "META", "timestamp": "2023-08-10T04:00:00+00:00", "open": 307.94, "high": 312.339, "low": 303.87, "close": 305.74, "volume": 14358897.0, "trade_count": 211327.0, "vwap": 307.860934}, {"symbol": "META", "timestamp": "2023-08-11T04:00:00+00:00", "open": 302.57, "high": 304.72, "low": 300.36, "close": 301.64, "volume": 13998667.0, "trade_count": 221362.0, "vwap": 302.147729}], "ABT": [{"symbol": "ABT", "timestamp": "2023-08-04T04:00:00+00:00", "open": 107.32, "high": 108.78, "low": 107.28, "close": 107.65, "volume": 3192742.0, "trade_count": 42544.0, "vwap": 107.912149}, {"symbol": "ABT", "timestamp": "2023-08-07T04:00:00+00:00", "open": 107.99, "high": 108.59, "low": 107.63, "close": 108.45, "volume": 3632578.0, "trade_count": 47756.0, "vwap": 108.231156}, {"symbol": "ABT", "timestamp": "2023-08-08T04:00:00+00:00", "open": 107.6, "high": 107.6, "low": 103.67, "close": 105.58, "volume": 7544340.0, "trade_count": 93390.0, "vwap": 105.073219}, {"symbol": "ABT", "timestamp": "2023-08-09T04:00:00+00:00", "open": 105.5, "high": 106.9, "low": 105.18, "close": 105.3, "volume": 5135274.0, "trade_count": 56364.0, "vwap": 105.822923}, {"symbol": "ABT", "timestamp": "2023-08-10T04:00:00+00:00", "open": 105.48, "high": 107.0, "low": 104.62, "close": 104.74, "volume": 4708261.0, "trade_count": 53668.0, "vwap": 105.306734}, {"symbol": "ABT", "timestamp": "2023-08-11T04:00:00+00:00", "open": 104.22, "high": 105.41, "low": 103.69, "close": 105.31, "volume": 3457418.0, "trade_count": 44955.0, "vwap": 104.950372}], "BA": [{"symbol": "BA", "timestamp": "2023-08-04T04:00:00+00:00", "open": 232.29, "high": 234.91, "low": 230.08, "close": 231.36, "volume": 3454937.0, "trade_count": 55844.0, "vwap": 232.35235}, {"symbol": "BA", "timestamp": "2023-08-07T04:00:00+00:00", "open": 232.74, "high": 238.98, "low": 232.74, "close": 238.25, "volume": 6069444.0, "trade_count": 87505.0, "vwap": 237.399191}, {"symbol": "BA", "timestamp": "2023-08-08T04:00:00+00:00", "open": 236.52, "high": 240.73, "low": 236.0, "close": 238.04, "volume": 5150025.0, "trade_count": 76073.0, "vwap": 238.361415}, {"symbol": "BA", "timestamp": "2023-08-09T04:00:00+00:00", "open": 238.54, "high": 241.24, "low": 236.4061, "close": 237.86, "volume": 4046008.0, "trade_count": 57988.0, "vwap": 238.566345}, {"symbol": "BA", "timestamp": "2023-08-10T04:00:00+00:00", "open": 238.45, "high": 241.58, "low": 237.04, "close": 238.26, "volume": 3710810.0, "trade_count": 53951.0, "vwap": 238.984685}, {"symbol": "BA", "timestamp": "2023-08-11T04:00:00+00:00", "open": 237.61, "high": 238.26, "low": 235.12, "close": 235.72, "volume": 2629577.0, "trade_count": 45609.0, "vwap": 236.222999}], "LMT": [{"symbol": "LMT", "timestamp": "2023-08-04T04:00:00+00:00", "open": 448.58, "high": 450.29, "low": 445.31, "close": 445.72, "volume": 831634.0, "trade_count": 27052.0, "vwap": 447.277704}, {"symbol": "LMT", "timestamp": "2023-08-07T04:00:00+00:00", "open": 447.32, "high": 450.47, "low": 446.276, "close": 449.78, "volume": 746806.0, "trade_count": 23755.0, "vwap": 449.208075}, {"symbol": "LMT", "timestamp": "2023-08-08T04:00:00+00:00", "open": 449.0, "high": 450.51, "low": 447.57, "close": 449.47, "volume": 791658.0, "trade_count": 26304.0, "vwap": 449.231138}, {"symbol": "LMT", "timestamp": "2023-08-09T04:00:00+00:00", "open": 450.08, "high": 454.05, "low": 449.99, "close": 452.81, "volume": 1212000.0, "trade_count": 29938.0, "vwap": 452.639945}, {"symbol": "LMT", "timestamp": "2023-08-10T04:00:00+00:00", "open": 452.0, "high": 453.97, "low": 449.26, "close": 450.05, "volume": 688916.0, "trade_count": 23098.0, "vwap": 451.124626}, {"symbol": "LMT", "timestamp": "2023-08-11T04:00:00+00:00", "open": 451.18, "high": 454.09, "low": 450.52, "close": 454.05, "volume": 687616.0, "trade_count": 23312.0, "vwap": 453.196245}], "OXY": [{"symbol": "OXY", "timestamp": "2023-08-04T04:00:00+00:00", "open": 62.6, "high": 64.525, "low": 62.52, "close": 63.52, "volume": 14233566.0, "trade_count": 121902.0, "vwap": 63.845091}, {"symbol": "OXY", "timestamp": "2023-08-07T04:00:00+00:00", "open": 63.82, "high": 64.29, "low": 63.531, "close": 63.9, "volume": 8880331.0, "trade_count": 91410.0, "vwap": 63.864827}, {"symbol": "OXY", "timestamp": "2023-08-08T04:00:00+00:00", "open": 63.0, "high": 63.895, "low": 62.44, "close": 63.75, "volume": 7307419.0, "trade_count": 76550.0, "vwap": 63.385268}, {"symbol": "OXY", "timestamp": "2023-08-09T04:00:00+00:00", "open": 64.2, "high": 65.07, "low": 63.68, "close": 63.81, "volume": 10760510.0, "trade_count": 95014.0, "vwap": 64.289241}, {"symbol": "OXY", "timestamp": "2023-08-10T04:00:00+00:00", "open": 63.95, "high": 64.61, "low": 63.25, "close": 63.73, "volume": 7611121.0, "trade_count": 72436.0, "vwap": 63.977611}, {"symbol": "OXY", "timestamp": "2023-08-11T04:00:00+00:00", "open": 64.0, "high": 66.025, "low": 64.0, "close": 65.84, "volume": 17046224.0, "trade_count": 144455.0, "vwap": 65.419599}], "TMUS": [{"symbol": "TMUS", "timestamp": "2023-08-04T04:00:00+00:00", "open": 135.79, "high": 136.47, "low": 134.46, "close": 134.6, "volume": 3218979.0, "trade_count": 48508.0, "vwap": 135.337778}, {"symbol": "TMUS", "timestamp": "2023-08-07T04:00:00+00:00", "open": 135.46, "high": 137.175, "low": 135.01, "close": 136.65, "volume": 3564661.0, "trade_count": 51304.0, "vwap": 136.526095}, {"symbol": "TMUS", "timestamp": "2023-08-08T04:00:00+00:00", "open": 136.49, "high": 137.57, "low": 136.19, "close": 136.26, "volume": 3242592.0, "trade_count": 52848.0, "vwap": 136.607948}, {"symbol": "TMUS", "timestamp": "2023-08-09T04:00:00+00:00", "open": 136.23, "high": 138.36, "low": 136.08, "close": 137.71, "volume": 4125616.0, "trade_count": 48626.0, "vwap": 137.541236}, {"symbol": "TMUS", "timestamp": "2023-08-10T04:00:00+00:00", "open": 138.65, "high": 139.44, "low": 137.58, "close": 137.73, "volume": 2492978.0, "trade_count": 43548.0, "vwap": 138.214205}, {"symbol": "TMUS", "timestamp": "2023-08-11T04:00:00+00:00", "open": 137.08, "high": 138.57, "low": 137.02, "close": 138.375, "volume": 2274615.0, "trade_count": 50502.0, "vwap": 138.074138}], "T": [{"symbol": "T", "timestamp": "2023-08-04T04:00:00+00:00", "open": 14.05, "high": 14.11, "low": 14.0, "close": 14.0, "volume": 38509614.0, "trade_count": 120492.0, "vwap": 14.032816}, {"symbol": "T", "timestamp": "2023-08-07T04:00:00+00:00", "open": 14.01, "high": 14.09, "low": 13.89, "close": 14.01, "volume": 38133442.0, "trade_count": 127992.0, "vwap": 13.981156}, {"symbol": "T", "timestamp": "2023-08-08T04:00:00+00:00", "open": 13.94, "high": 14.2, "low": 13.94, "close": 14.18, "volume": 39090432.0, "trade_count": 109814.0, "vwap": 14.084772}, {"symbol": "T", "timestamp": "2023-08-09T04:00:00+00:00", "open": 14.17, "high": 14.35, "low": 14.15, "close": 14.27, "volume": 33973899.0, "trade_count": 96250.0, "vwap": 14.266294}, {"symbol": "T", "timestamp": "2023-08-10T04:00:00+00:00", "open": 14.29, "high": 14.35, "low": 14.17, "close": 14.17, "volume": 33556423.0, "trade_count": 101541.0, "vwap": 14.23968}, {"symbol": "T", "timestamp": "2023-08-11T04:00:00+00:00", "open": 14.145, "high": 14.4, "low": 14.12, "close": 14.37, "volume": 31154105.0, "trade_count": 91532.0, "vwap": 14.296823}], "CMCSA": [{"symbol": "CMCSA", "timestamp": "2023-08-04T04:00:00+00:00", "open": 45.25, "high": 45.55, "low": 44.785, "close": 44.84, "volume": 12516192.0, "trade_count": 97388.0, "vwap": 45.087971}, {"symbol": "CMCSA", "timestamp": "2023-08-07T04:00:00+00:00", "open": 45.14, "high": 45.6, "low": 45.085, "close": 45.45, "volume": 12530034.0, "trade_count": 79518.0, "vwap": 45.41055}, {"symbol": "CMCSA", "timestamp": "2023-08-08T04:00:00+00:00", "open": 45.3, "high": 45.605, "low": 45.15, "close": 45.4, "volume": 19889044.0, "trade_count": 122460.0, "vwap": 45.433486}, {"symbol": "CMCSA", "timestamp": "2023-08-09T04:00:00+00:00", "open": 45.395, "high": 45.64, "low": 45.17, "close": 45.28, "volume": 15187094.0, "trade_count": 97599.0, "vwap": 45.390282}, {"symbol": "CMCSA", "timestamp": "2023-08-10T04:00:00+00:00", "open": 45.67, "high": 46.53, "low": 45.67, "close": 45.93, "volume": 16149723.0, "trade_count": 123422.0, "vwap": 46.046458}, {"symbol": "CMCSA", "timestamp": "2023-08-11T04:00:00+00:00", "open": 45.68, "high": 46.23, "low": 45.565, "close": 46.03, "volume": 13460072.0, "trade_count": 103268.0, "vwap": 45.98569}], "GOOGL": [{"symbol": "GOOGL", "timestamp": "2023-08-04T04:00:00+00:00", "open": 129.28, "high": 131.51, "low": 127.91, "close": 128.11, "volume": 25956078.0, "trade_count": 346948.0, "vwap": 129.31957}, {"symbol": "GOOGL", "timestamp": "2023-08-07T04:00:00+00:00", "open": 129.16, "high": 131.61, "low": 129.02, "close": 131.53, "volume": 22763036.0, "trade_count": 283234.0, "vwap": 130.767057}, {"symbol": "GOOGL", "timestamp": "2023-08-08T04:00:00+00:00", "open": 130.62, "high": 131.51, "low": 129.545, "close": 131.4, "volume": 23542365.0, "trade_count": 274046.0, "vwap": 130.872829}, {"symbol": "GOOGL", "timestamp": "2023-08-09T04:00:00+00:00", "open": 131.66, "high": 132.04, "low": 129.0, "close": 129.66, "volume": 24926602.0, "trade_count": 275790.0, "vwap": 130.316334}, {"symbol": "GOOGL", "timestamp": "2023-08-10T04:00:00+00:00", "open": 131.32, "high": 132.05, "low": 129.45, "close": 129.69, "volume": 20858745.0, "trade_count": 256299.0, "vwap": 130.419014}, {"symbol": "GOOGL", "timestamp": "2023-08-11T04:00:00+00:00", "open": 128.66, "high": 129.93, "low": 128.17, "close": 129.56, "volume": 19472502.0, "trade_count": 232911.0, "vwap": 129.213393}], "MO": [{"symbol": "MO", "timestamp": "2023-08-04T04:00:00+00:00", "open": 44.27, "high": 44.495, "low": 43.915, "close": 44.0, "volume": 8006752.0, "trade_count": 63273.0, "vwap": 44.127294}, {"symbol": "MO", "timestamp": "2023-08-07T04:00:00+00:00", "open": 44.03, "high": 44.23, "low": 43.91, "close": 44.12, "volume": 7874865.0, "trade_count": 62838.0, "vwap": 44.092826}, {"symbol": "MO", "timestamp": "2023-08-08T04:00:00+00:00", "open": 44.0, "high": 44.31, "low": 43.725, "close": 44.24, "volume": 6105298.0, "trade_count": 55729.0, "vwap": 44.071027}, {"symbol": "MO", "timestamp": "2023-08-09T04:00:00+00:00", "open": 44.26, "high": 44.6, "low": 44.07, "close": 44.09, "volume": 5413268.0, "trade_count": 50264.0, "vwap": 44.298592}, {"symbol": "MO", "timestamp": "2023-08-10T04:00:00+00:00", "open": 44.11, "high": 44.34, "low": 43.83, "close": 43.92, "volume": 6597916.0, "trade_count": 53901.0, "vwap": 44.064734}, {"symbol": "MO", "timestamp": "2023-08-11T04:00:00+00:00", "open": 43.89, "high": 43.92, "low": 43.62, "close": 43.73, "volume": 7124432.0, "trade_count": 55754.0, "vwap": 43.718822}], "VZ": [{"symbol": "VZ", "timestamp": "2023-08-04T04:00:00+00:00", "open": 33.0, "high": 33.03, "low": 32.53, "close": 32.62, "volume": 24315039.0, "trade_count": 136221.0, "vwap": 32.724761}, {"symbol": "VZ", "timestamp": "2023-08-07T04:00:00+00:00", "open": 32.65, "high": 32.83, "low": 32.18, "close": 32.53, "volume": 24318645.0, "trade_count": 129067.0, "vwap": 32.454619}, {"symbol": "VZ", "timestamp": "2023-08-08T04:00:00+00:00", "open": 32.45, "high": 32.81, "low": 32.43, "close": 32.57, "volume": 22236298.0, "trade_count": 110722.0, "vwap": 32.561327}, {"symbol": "VZ", "timestamp": "2023-08-09T04:00:00+00:00", "open": 32.51, "high": 32.83, "low": 32.34, "close": 32.71, "volume": 20868451.0, "trade_count": 105077.0, "vwap": 32.643333}, {"symbol": "VZ", "timestamp": "2023-08-10T04:00:00+00:00", "open": 32.85, "high": 33.32, "low": 32.82, "close": 33.02, "volume": 19031591.0, "trade_count": 113781.0, "vwap": 33.051082}, {"symbol": "VZ", "timestamp": "2023-08-11T04:00:00+00:00", "open": 32.96, "high": 33.42, "low": 32.945, "close": 33.36, "volume": 15197632.0, "trade_count": 92122.0, "vwap": 33.290236}]}, "collected_at": "2023-08-13T21:17:19.249659"}